Metadata-Version: 2.1
Name: sayhelloracheloooo
Version: 1.1.6
Summary: A lightweight third-party broadcast library
Home-page: https://github.com/Undertone0809/broadcast-service
Author: rachel
Author-email: rachel@163.com
License: Apache 2.0
Keywords: print,changshidayin
Platform: UNKNOWN
Classifier: Development Status :: 3 - Alpha
Classifier: Intended Audience :: Developers
Classifier: Programming Language :: Python :: 3
Classifier: Programming Language :: Python :: 3.7
Classifier: Programming Language :: Python :: 3.8
Classifier: Programming Language :: Python :: 3.9
Classifier: Programming Language :: Python :: 3.10
Classifier: Programming Language :: Python :: 3 :: Only
Classifier: License :: OSI Approved :: MIT License
Classifier: Operating System :: OS Independent
